[{"__symbolic":"module","version":3,"metadata":{"IntegralUITabStripModule":{"__symbolic":"class","decorators":[{"__symbolic":"call","expression":{"__symbolic":"reference","module":"@angular/core","name":"NgModule"},"arguments":[{"imports":[{"__symbolic":"reference","module":"@angular/common","name":"CommonModule"},{"__symbolic":"reference","module":"@angular/forms","name":"FormsModule"},{"__symbolic":"reference","module":"./integralui.core.module","name":"IntegralUICoreModule"}],"declarations":[{"__symbolic":"reference","module":"./components/integralui.tab","name":"IntegralUITab"},{"__symbolic":"reference","module":"./components/integralui.tabstrip","name":"IntegralUITabStrip"}],"exports":[{"__symbolic":"reference","module":"./components/integralui.core","name":"IntegralUIFocus"},{"__symbolic":"reference","module":"./components/integralui.core","name":"IntegralUITemplate"},{"__symbolic":"reference","module":"./components/integralui.tab","name":"IntegralUITab"},{"__symbolic":"reference","module":"./components/integralui.tabstrip","name":"IntegralUITabStrip"}]}]}]}}},{"__symbolic":"module","version":1,"metadata":{"IntegralUITabStripModule":{"__symbolic":"class","decorators":[{"__symbolic":"call","expression":{"__symbolic":"reference","module":"@angular/core","name":"NgModule"},"arguments":[{"imports":[{"__symbolic":"reference","module":"@angular/common","name":"CommonModule"},{"__symbolic":"reference","module":"@angular/forms","name":"FormsModule"},{"__symbolic":"reference","module":"./integralui.core.module","name":"IntegralUICoreModule"}],"declarations":[{"__symbolic":"reference","module":"./components/integralui.tab","name":"IntegralUITab"},{"__symbolic":"reference","module":"./components/integralui.tabstrip","name":"IntegralUITabStrip"}],"exports":[{"__symbolic":"reference","module":"./components/integralui.core","name":"IntegralUIFocus"},{"__symbolic":"reference","module":"./components/integralui.core","name":"IntegralUITemplate"},{"__symbolic":"reference","module":"./components/integralui.tab","name":"IntegralUITab"},{"__symbolic":"reference","module":"./components/integralui.tabstrip","name":"IntegralUITabStrip"}]}]}]}}}]