[{"__symbolic":"module","version":3,"metadata":{"IntegralUIComboBox":{"__symbolic":"class","extends":{"__symbolic":"reference","module":"./integralui.core","name":"IntegralUIBaseComponent"},"decorators":[{"__symbolic":"call","expression":{"__symbolic":"reference","module":"@angular/core","name":"Component"},"arguments":[{"selector":"iui-combobox","template":"\n\t\t<div [ngClass]=\"getControlClass()\" #control>\n\t\t\t<iui-header [controlStyle]=\"getCurrentHeaderStyle()\" [enabled]=\"enabled\" [icon]=\"getComboIcon()\" [iconUrl]=\"getComboIconUrl()\" [text]=\"getComboText()\" (mouseDown)=\"comboClick($event)\" [animationType]=\"'arrow'\" #header>\n\t\t\t</iui-header>\n\t\t\t<div [ngClass]=\"getContentClass()\" [ngStyle]=\"{ 'border-width': contentBorder, 'display': contentDisplay, 'height': contentHeight, 'opacity': contentOpacity, 'overflow-y': contentOverflowY, 'width': getDropDownWidth() + 'px' }\" tabindex=\"999\" (blur)=\"dropDownBlurEvent($event)\" #dropdown> \n\t\t\t\t<ng-content></ng-content>\n\t\t\t</div> \n\t\t</div>\n\t","inputs":["controlStyle","data","enabled","name","state"],"encapsulation":{"__symbolic":"select","expression":{"__symbolic":"reference","module":"@angular/core","name":"ViewEncapsulation"},"member":"None"}}]}],"members":{"controlElem":[{"__symbolic":"property","decorators":[{"__symbolic":"call","expression":{"__symbolic":"reference","module":"@angular/core","name":"ViewChild"},"arguments":["control",{"read":{"__symbolic":"reference","module":"@angular/core","name":"ElementRef"}}]}]}],"header":[{"__symbolic":"property","decorators":[{"__symbolic":"call","expression":{"__symbolic":"reference","module":"@angular/core","name":"ViewChild"},"arguments":["header"]}]}],"headerElem":[{"__symbolic":"property","decorators":[{"__symbolic":"call","expression":{"__symbolic":"reference","module":"@angular/core","name":"ViewChild"},"arguments":["header",{"read":{"__symbolic":"reference","module":"@angular/core","name":"ElementRef"}}]}]}],"headerRef":[{"__symbolic":"property","decorators":[{"__symbolic":"call","expression":{"__symbolic":"reference","module":"@angular/core","name":"ViewChild"},"arguments":["header",{"read":{"__symbolic":"reference","module":"@angular/core","name":"ViewContainerRef"}}]}]}],"dropDownElem":[{"__symbolic":"property","decorators":[{"__symbolic":"call","expression":{"__symbolic":"reference","module":"@angular/core","name":"ViewChild"},"arguments":["dropdown",{"read":{"__symbolic":"reference","module":"@angular/core","name":"ElementRef"}}]}]}],"contentList":[{"__symbolic":"property","decorators":[{"__symbolic":"call","expression":{"__symbolic":"reference","module":"@angular/core","name":"ContentChildren"},"arguments":[{"__symbolic":"reference","module":"./integralui.core","name":"IntegralUIItem"}]}]}],"dropDownHeight":[{"__symbolic":"property","decorators":[{"__symbolic":"call","expression":{"__symbolic":"reference","module":"@angular/core","name":"Input"}}]}],"integralHeight":[{"__symbolic":"property","decorators":[{"__symbolic":"call","expression":{"__symbolic":"reference","module":"@angular/core","name":"Input"}}]}],"items":[{"__symbolic":"property","decorators":[{"__symbolic":"call","expression":{"__symbolic":"reference","module":"@angular/core","name":"Input"}}]}],"maxDropDownItems":[{"__symbolic":"property","decorators":[{"__symbolic":"call","expression":{"__symbolic":"reference","module":"@angular/core","name":"Input"}}]}],"dropDownWidth":[{"__symbolic":"property","decorators":[{"__symbolic":"call","expression":{"__symbolic":"reference","module":"@angular/core","name":"Input"}}]}],"expanded":[{"__symbolic":"property","decorators":[{"__symbolic":"call","expression":{"__symbolic":"reference","module":"@angular/core","name":"Input"}}]}],"selectedIndex":[{"__symbolic":"property","decorators":[{"__symbolic":"call","expression":{"__symbolic":"reference","module":"@angular/core","name":"Input"}}]}],"selectedItem":[{"__symbolic":"property","decorators":[{"__symbolic":"call","expression":{"__symbolic":"reference","module":"@angular/core","name":"Input"}}]}],"click":[{"__symbolic":"property","decorators":[{"__symbolic":"call","expression":{"__symbolic":"reference","module":"@angular/core","name":"Output"}}]}],"dropDownClosed":[{"__symbolic":"property","decorators":[{"__symbolic":"call","expression":{"__symbolic":"reference","module":"@angular/core","name":"Output"}}]}],"dropDownClosing":[{"__symbolic":"property","decorators":[{"__symbolic":"call","expression":{"__symbolic":"reference","module":"@angular/core","name":"Output"}}]}],"dropDownOpened":[{"__symbolic":"property","decorators":[{"__symbolic":"call","expression":{"__symbolic":"reference","module":"@angular/core","name":"Output"}}]}],"dropDownOpening":[{"__symbolic":"property","decorators":[{"__symbolic":"call","expression":{"__symbolic":"reference","module":"@angular/core","name":"Output"}}]}],"selectedItemChanged":[{"__symbolic":"property","decorators":[{"__symbolic":"call","expression":{"__symbolic":"reference","module":"@angular/core","name":"Output"}}]}],"selectedIndexChanged":[{"__symbolic":"property","decorators":[{"__symbolic":"call","expression":{"__symbolic":"reference","module":"@angular/core","name":"Output"}}]}],"__ctor__":[{"__symbolic":"constructor","parameters":[{"__symbolic":"reference","module":"../services/integralui.common.service","name":"IntegralUICommonService"},{"__symbolic":"reference","module":"@angular/core","name":"ComponentFactoryResolver"}]}],"ngOnInit":[{"__symbolic":"method"}],"ngAfterViewInit":[{"__symbolic":"method"}],"ngAfterContentInit":[{"__symbolic":"method"}],"ngOnDestroy":[{"__symbolic":"method"}],"attachItemEvents":[{"__symbolic":"method"}],"comboClick":[{"__symbolic":"method"}],"dropDownBlurEvent":[{"__symbolic":"method"}],"callBeforeEvent":[{"__symbolic":"method"}],"callAfterEvent":[{"__symbolic":"method"}],"closeDropDown":[{"__symbolic":"method"}],"openDropDown":[{"__symbolic":"method"}],"getComboIcon":[{"__symbolic":"method"}],"getComboIconUrl":[{"__symbolic":"method"}],"getComboText":[{"__symbolic":"method"}],"isIndexInRange":[{"__symbolic":"method"}],"getDropDownWidth":[{"__symbolic":"method"}],"calcBlockHeight":[{"__symbolic":"method"}],"getDropDownHeight":[{"__symbolic":"method"}],"toggleContent":[{"__symbolic":"method"}],"clearSelection":[{"__symbolic":"method"}],"updateSelectedIndex":[{"__symbolic":"method"}],"updateSelection":[{"__symbolic":"method"}],"updateContentClass":[{"__symbolic":"method"}],"getContentClass":[{"__symbolic":"method"}],"getContentStyle":[{"__symbolic":"method"}],"getHeaderClass":[{"__symbolic":"method"}],"getHeaderGeneralStyle":[{"__symbolic":"method"}],"getHeaderStyle":[{"__symbolic":"method"}],"getCurrentHeaderStyle":[{"__symbolic":"method"}],"getItemStyle":[{"__symbolic":"method"}],"getItemGeneralStyle":[{"__symbolic":"method"}],"getItemContentStyle":[{"__symbolic":"method"}],"updateStyle":[{"__symbolic":"method"}]}}}},{"__symbolic":"module","version":1,"metadata":{"IntegralUIComboBox":{"__symbolic":"class","extends":{"__symbolic":"reference","module":"./integralui.core","name":"IntegralUIBaseComponent"},"decorators":[{"__symbolic":"call","expression":{"__symbolic":"reference","module":"@angular/core","name":"Component"},"arguments":[{"selector":"iui-combobox","template":"\n\t\t<div [ngClass]=\"getControlClass()\" #control>\n\t\t\t<iui-header [controlStyle]=\"getCurrentHeaderStyle()\" [enabled]=\"enabled\" [icon]=\"getComboIcon()\" [iconUrl]=\"getComboIconUrl()\" [text]=\"getComboText()\" (mouseDown)=\"comboClick($event)\" [animationType]=\"'arrow'\" #header>\n\t\t\t</iui-header>\n\t\t\t<div [ngClass]=\"getContentClass()\" [ngStyle]=\"{ 'border-width': contentBorder, 'display': contentDisplay, 'height': contentHeight, 'opacity': contentOpacity, 'overflow-y': contentOverflowY, 'width': getDropDownWidth() + 'px' }\" tabindex=\"999\" (blur)=\"dropDownBlurEvent($event)\" #dropdown> \n\t\t\t\t<ng-content></ng-content>\n\t\t\t</div> \n\t\t</div>\n\t","inputs":["controlStyle","data","enabled","name","state"],"encapsulation":{"__symbolic":"select","expression":{"__symbolic":"reference","module":"@angular/core","name":"ViewEncapsulation"},"member":"None"}}]}],"members":{"controlElem":[{"__symbolic":"property","decorators":[{"__symbolic":"call","expression":{"__symbolic":"reference","module":"@angular/core","name":"ViewChild"},"arguments":["control",{"read":{"__symbolic":"reference","module":"@angular/core","name":"ElementRef"}}]}]}],"header":[{"__symbolic":"property","decorators":[{"__symbolic":"call","expression":{"__symbolic":"reference","module":"@angular/core","name":"ViewChild"},"arguments":["header"]}]}],"headerElem":[{"__symbolic":"property","decorators":[{"__symbolic":"call","expression":{"__symbolic":"reference","module":"@angular/core","name":"ViewChild"},"arguments":["header",{"read":{"__symbolic":"reference","module":"@angular/core","name":"ElementRef"}}]}]}],"headerRef":[{"__symbolic":"property","decorators":[{"__symbolic":"call","expression":{"__symbolic":"reference","module":"@angular/core","name":"ViewChild"},"arguments":["header",{"read":{"__symbolic":"reference","module":"@angular/core","name":"ViewContainerRef"}}]}]}],"dropDownElem":[{"__symbolic":"property","decorators":[{"__symbolic":"call","expression":{"__symbolic":"reference","module":"@angular/core","name":"ViewChild"},"arguments":["dropdown",{"read":{"__symbolic":"reference","module":"@angular/core","name":"ElementRef"}}]}]}],"contentList":[{"__symbolic":"property","decorators":[{"__symbolic":"call","expression":{"__symbolic":"reference","module":"@angular/core","name":"ContentChildren"},"arguments":[{"__symbolic":"reference","module":"./integralui.core","name":"IntegralUIItem"}]}]}],"dropDownHeight":[{"__symbolic":"property","decorators":[{"__symbolic":"call","expression":{"__symbolic":"reference","module":"@angular/core","name":"Input"}}]}],"integralHeight":[{"__symbolic":"property","decorators":[{"__symbolic":"call","expression":{"__symbolic":"reference","module":"@angular/core","name":"Input"}}]}],"items":[{"__symbolic":"property","decorators":[{"__symbolic":"call","expression":{"__symbolic":"reference","module":"@angular/core","name":"Input"}}]}],"maxDropDownItems":[{"__symbolic":"property","decorators":[{"__symbolic":"call","expression":{"__symbolic":"reference","module":"@angular/core","name":"Input"}}]}],"dropDownWidth":[{"__symbolic":"property","decorators":[{"__symbolic":"call","expression":{"__symbolic":"reference","module":"@angular/core","name":"Input"}}]}],"expanded":[{"__symbolic":"property","decorators":[{"__symbolic":"call","expression":{"__symbolic":"reference","module":"@angular/core","name":"Input"}}]}],"selectedIndex":[{"__symbolic":"property","decorators":[{"__symbolic":"call","expression":{"__symbolic":"reference","module":"@angular/core","name":"Input"}}]}],"selectedItem":[{"__symbolic":"property","decorators":[{"__symbolic":"call","expression":{"__symbolic":"reference","module":"@angular/core","name":"Input"}}]}],"click":[{"__symbolic":"property","decorators":[{"__symbolic":"call","expression":{"__symbolic":"reference","module":"@angular/core","name":"Output"}}]}],"dropDownClosed":[{"__symbolic":"property","decorators":[{"__symbolic":"call","expression":{"__symbolic":"reference","module":"@angular/core","name":"Output"}}]}],"dropDownClosing":[{"__symbolic":"property","decorators":[{"__symbolic":"call","expression":{"__symbolic":"reference","module":"@angular/core","name":"Output"}}]}],"dropDownOpened":[{"__symbolic":"property","decorators":[{"__symbolic":"call","expression":{"__symbolic":"reference","module":"@angular/core","name":"Output"}}]}],"dropDownOpening":[{"__symbolic":"property","decorators":[{"__symbolic":"call","expression":{"__symbolic":"reference","module":"@angular/core","name":"Output"}}]}],"selectedItemChanged":[{"__symbolic":"property","decorators":[{"__symbolic":"call","expression":{"__symbolic":"reference","module":"@angular/core","name":"Output"}}]}],"selectedIndexChanged":[{"__symbolic":"property","decorators":[{"__symbolic":"call","expression":{"__symbolic":"reference","module":"@angular/core","name":"Output"}}]}],"__ctor__":[{"__symbolic":"constructor","parameters":[{"__symbolic":"reference","module":"../services/integralui.common.service","name":"IntegralUICommonService"},{"__symbolic":"reference","module":"@angular/core","name":"ComponentFactoryResolver"}]}],"ngOnInit":[{"__symbolic":"method"}],"ngAfterViewInit":[{"__symbolic":"method"}],"ngAfterContentInit":[{"__symbolic":"method"}],"ngOnDestroy":[{"__symbolic":"method"}],"attachItemEvents":[{"__symbolic":"method"}],"comboClick":[{"__symbolic":"method"}],"dropDownBlurEvent":[{"__symbolic":"method"}],"callBeforeEvent":[{"__symbolic":"method"}],"callAfterEvent":[{"__symbolic":"method"}],"closeDropDown":[{"__symbolic":"method"}],"openDropDown":[{"__symbolic":"method"}],"getComboIcon":[{"__symbolic":"method"}],"getComboIconUrl":[{"__symbolic":"method"}],"getComboText":[{"__symbolic":"method"}],"isIndexInRange":[{"__symbolic":"method"}],"getDropDownWidth":[{"__symbolic":"method"}],"calcBlockHeight":[{"__symbolic":"method"}],"getDropDownHeight":[{"__symbolic":"method"}],"toggleContent":[{"__symbolic":"method"}],"clearSelection":[{"__symbolic":"method"}],"updateSelectedIndex":[{"__symbolic":"method"}],"updateSelection":[{"__symbolic":"method"}],"updateContentClass":[{"__symbolic":"method"}],"getContentClass":[{"__symbolic":"method"}],"getContentStyle":[{"__symbolic":"method"}],"getHeaderClass":[{"__symbolic":"method"}],"getHeaderGeneralStyle":[{"__symbolic":"method"}],"getHeaderStyle":[{"__symbolic":"method"}],"getCurrentHeaderStyle":[{"__symbolic":"method"}],"getItemStyle":[{"__symbolic":"method"}],"getItemGeneralStyle":[{"__symbolic":"method"}],"getItemContentStyle":[{"__symbolic":"method"}],"updateStyle":[{"__symbolic":"method"}]}}}}]